cacert.pem
lib64/libcpr.a
lib64/libfmt.a
lib64/libCCDialect.a
lib64/libOptTransforms.a
lib64/libQuakeDialect.a
lib64/libOptCodeGen.a
lib64/pkgconfig/fmt.pc
lib64/cmake/cpr/cprConfig.cmake
lib64/cmake/cpr/cprTargets.cmake
lib64/cmake/cpr/cprConfigVersion.cmake
lib64/cmake/cpr/cprTargets-release.cmake
lib64/cmake/fmt/fmt-config-version.cmake
lib64/cmake/fmt/fmt-targets-release.cmake
lib64/cmake/fmt/fmt-config.cmake
lib64/cmake/fmt/fmt-targets.cmake
lib64/cmake/Crow/CrowTargets.cmake
lib64/cmake/Crow/Findasio.cmake
lib64/cmake/Crow/CrowConfig.cmake
lib/librest-remote-platform-server.so
lib/libnvqir-dm.so
lib/libcudaq.so
lib/libcudaq-em-default.so
lib/libnvqir-custatevec-kernels.so
lib/libcudaq-orca-qpu.so
lib/libcudaq-platform-mqpu.so
lib/libcudaq-ensmallen.so
lib/libnvqir-cusvsim-fp32.so
lib/libnvqir-nvidia-mgpu.so
lib/libnvqir-custatevec-fp64.so
lib/libnvqir.so
lib/libnvqir-nvidia-mgpu-fp32.so
lib/libcudaq-builder.so
lib/libnvqir-tensornet-mps.so
lib/libcudaq-serverhelper-ionq.so
lib/libnvqir-custatevec-fp32.so
lib/libCCDialect.a
lib/libcudaq-mlir-runtime.so
lib/libcudaq-platform-default.so
lib/libnvqir-qpp.so
lib/librest-remote-platform-client.so
lib/libcudaq-em-photonics.so
lib/libnvqir-tensornet.so
lib/libcudaq-remote-simulator-qpu.so
lib/libcudaq-serverhelper-iqm.so
lib/libcudaq-serverhelper-oqc.so
lib/libCUDAQuantumMLIRCAPI.a
lib/libcudaq-py-utils.so
lib/libcudaq-rest-qpu.so
lib/libOptTransforms.a
lib/libCUDAQTargetConfigUtil.a
lib/libcudaq-chemistry.so
lib/libcudaq-common.so
lib/libcudaq-spin.so
lib/libcudaq-serverhelper-quantinuum.so
lib/libQuakeDialect.a
lib/libnvqir-cusvsim-fp64.so
lib/libcudaq-nlopt.so
lib/libOptCodeGen.a
lib/libOptimBuilder.a
lib/libCUDAQSupport.a
lib/plugins/libcudaq-pyscf.so
lib/cmake/nvqir/NVQIRTargets-release.cmake
lib/cmake/nvqir/NVQIRConfig.cmake
lib/cmake/nvqir/NVQIRTargets.cmake
lib/cmake/cudaq/CUDAQSpinConfig.cmake
lib/cmake/cudaq/CMakeDetermineCUDAQCompiler.cmake
cuda_quantum-0.8.0.dist-info/METADATA
cuda_quantum-0.8.0.dist-info/WHEEL
cuda_quantum-0.8.0.dist-info/RECORD
cuda_quantum-0.8.0.dist-info/licenses/LICENSE
cuda_quantum-0.8.0.dist-info/licenses/CITATION.cff
cuda_quantum-0.8.0.dist-info/licenses/NOTICE
