Metadata-Version: 2.1
Name: cuda-quantum
Version: 0.8.0
Summary: Python bindings for the CUDA-Q toolkit for heterogeneous quantum-classical workflows.
Keywords: cuda-quantum,cuda,quantum,quantum computing,nvidia,high-performance computing
Author: NVIDIA Corporation & Affiliates
Maintainer: NVIDIA Corporation & Affiliates
License: Apache License Version 2.0
Project-URL: Homepage, https://developer.nvidia.com/cuda-quantum
Project-URL: Documentation, https://nvidia.github.io/cuda-quantum
Project-URL: Repository, https://github.com/NVIDIA/cuda-quantum
Project-URL: Releases, https://nvidia.github.io/cuda-quantum/latest/releases.html
Requires-Python: >=3.8
Requires-Dist: astpretty~=3.0
Requires-Dist: cuquantum-cu11~=24.03
Requires-Dist: graphlib-backport>=1.0
Requires-Dist: numpy>=1.24
Requires-Dist: requests>=2.31
Requires-Dist: nvidia-cublas-cu11==11.11.3.6; platform_machine == "x86_64"
Requires-Dist: nvidia-cuda-runtime-cu11==11.8.89; platform_machine == "x86_64"
Requires-Dist: nvidia-cusolver-cu11==11.4.1.48; platform_machine == "x86_64"
Requires-Dist: scipy==1.10.1; extra == "chemistry"
Requires-Dist: openfermionpyscf==0.5; extra == "chemistry"
Requires-Dist: h5py<3.11; extra == "chemistry"
Requires-Dist: qutip<5; extra == "visualization"
Requires-Dist: matplotlib>=3.5; extra == "visualization"
Provides-Extra: chemistry
Provides-Extra: visualization
